pystarboundmap/__init__.py
pystarboundmap/config.py
pystarboundmap/data.py
pystarboundmap/gui.py
pystarboundmap-1.0.0b7.dist-info/COPYING.txt
pystarboundmap-1.0.0b7.dist-info/METADATA
pystarboundmap-1.0.0b7.dist-info/WHEEL
pystarboundmap-1.0.0b7.dist-info/entry_points.txt
pystarboundmap-1.0.0b7.dist-info/top_level.txt
pystarboundmap-1.0.0b7.dist-info/RECORD
