Metadata-Version: 2.1
Name: pystarboundmap
Version: 1.0.0b7
Summary: Starbound Map Viewer
Home-page: https://github.com/apocalyptech/pystarboundmap
Author: CJ Kucera
Author-email: cj@apocalyptech.com
License: BSD License
Platform: UNKNOWN
Classifier: Development Status :: 4 - Beta
Classifier: Environment :: X11 Applications :: Qt
Classifier: Intended Audience :: End Users/Desktop
Classifier: License :: OSI Approved :: BSD License
Classifier: Natural Language :: English
Classifier: Operating System :: OS Independent
Classifier: Programming Language :: Python
Classifier: Programming Language :: Python :: 3 :: Only
Classifier: Topic :: Games/Entertainment
Classifier: Topic :: Utilities
Requires-Dist: Pillow (~=5.3)
Requires-Dist: PyQt5 (~=5.11)
Requires-Dist: appdirs (~=1.4)
Requires-Dist: timeago (~=1.0)
Requires-Dist: py-starbound (~=1.0)
